bixi/__init__.py
bixi/completions/__init__.py
bixi/completions/base_serving.py
bixi/completions/chat_serving.py
bixi/completions/completion_serving.py
bixi/completions/protocol.py
bixi/completions/serve.py
heliumos_bixi_completions-0.4.0.dist-info/METADATA
heliumos_bixi_completions-0.4.0.dist-info/WHEEL
heliumos_bixi_completions-0.4.0.dist-info/top_level.txt
heliumos_bixi_completions-0.4.0.dist-info/RECORD
